mergeLine/__init__.py
mergeLine/tools.py
mergeLines-2.1.6.dist-info/METADATA
mergeLines-2.1.6.dist-info/WHEEL
mergeLines-2.1.6.dist-info/top_level.txt
mergeLines-2.1.6.dist-info/RECORD
