Metadata-Version: 2.1
Name: mergeLines
Version: 2.1.6
Summary: merge lines after houghlinesp
Home-page: UNKNOWN
License: UNKNOWN
Platform: UNKNOWN
